{
  "response": {
    "total": 9084,
    "dateFormat": "YYYY-MM-DD",
    "frequency": "daily",
    "data": [
      {
        "period": "2026-05-18",
        "duoarea": "RGC",
        "area-name": "NA",
        "product": "EPJK",
        "product-name": "Kerosene-Type Jet Fuel",
        "process": "PF4",
        "process-name": "Spot Price FOB",
        "series": "EER_EPJK_PF4_RGC_DPG",
        "series-description": "U.S. Gulf Coast Kerosene-Type Jet Fuel Spot Price FOB (Dollars per Gallon)",
        "value": 4.191,
        "units": "$/GAL"
      },
      {
        "period": "2026-05-15",
        "duoarea": "RGC",
        "area-name": "NA",
        "product": "EPJK",
        "product-name": "Kerosene-Type Jet Fuel",
        "process": "PF4",
        "process-name": "Spot Price FOB",
        "series": "EER_EPJK_PF4_RGC_DPG",
        "series-description": "U.S. Gulf Coast Kerosene-Type Jet Fuel Spot Price FOB (Dollars per Gallon)",
        "value": 4.193,
        "units": "$/GAL"
      },
      {
        "period": "2026-05-14",
        "duoarea": "RGC",
        "area-name": "NA",
        "product": "EPJK",
        "product-name": "Kerosene-Type Jet Fuel",
        "process": "PF4",
        "process-name": "Spot Price FOB",
        "series": "EER_EPJK_PF4_RGC_DPG",
        "series-description": "U.S. Gulf Coast Kerosene-Type Jet Fuel Spot Price FOB (Dollars per Gallon)",
        "value": 4.075,
        "units": "$/GAL"
      },
      {
        "period": "2026-05-13",
        "duoarea": "RGC",
        "area-name": "NA",
        "product": "EPJK",
        "product-name": "Kerosene-Type Jet Fuel",
        "process": "PF4",
        "process-name": "Spot Price FOB",
        "series": "EER_EPJK_PF4_RGC_DPG",
        "series-description": "U.S. Gulf Coast Kerosene-Type Jet Fuel Spot Price FOB (Dollars per Gallon)",
        "value": 4.117,
        "units": "$/GAL"
      },
      {
        "period": "2026-05-12",
        "duoarea": "RGC",
        "area-name": "NA",
        "product": "EPJK",
        "product-name": "Kerosene-Type Jet Fuel",
        "process": "PF4",
        "process-name": "Spot Price FOB",
        "series": "EER_EPJK_PF4_RGC_DPG",
        "series-description": "U.S. Gulf Coast Kerosene-Type Jet Fuel Spot Price FOB (Dollars per Gallon)",
        "value": 4.265,
        "units": "$/GAL"
      },
      {
        "period": "2026-05-11",
        "duoarea": "RGC",
        "area-name": "NA",
        "product": "EPJK",
        "product-name": "Kerosene-Type Jet Fuel",
        "process": "PF4",
        "process-name": "Spot Price FOB",
        "series": "EER_EPJK_PF4_RGC_DPG",
        "series-description": "U.S. Gulf Coast Kerosene-Type Jet Fuel Spot Price FOB (Dollars per Gallon)",
        "value": 4.111,
        "units": "$/GAL"
      },
      {
        "period": "2026-05-08",
        "duoarea": "RGC",
        "area-name": "NA",
        "product": "EPJK",
        "product-name": "Kerosene-Type Jet Fuel",
        "process": "PF4",
        "process-name": "Spot Price FOB",
        "series": "EER_EPJK_PF4_RGC_DPG",
        "series-description": "U.S. Gulf Coast Kerosene-Type Jet Fuel Spot Price FOB (Dollars per Gallon)",
        "value": 3.992,
        "units": "$/GAL"
      },
      {
        "period": "2026-05-07",
        "duoarea": "RGC",
        "area-name": "NA",
        "product": "EPJK",
        "product-name": "Kerosene-Type Jet Fuel",
        "process": "PF4",
        "process-name": "Spot Price FOB",
        "series": "EER_EPJK_PF4_RGC_DPG",
        "series-description": "U.S. Gulf Coast Kerosene-Type Jet Fuel Spot Price FOB (Dollars per Gallon)",
        "value": 3.996,
        "units": "$/GAL"
      },
      {
        "period": "2026-05-06",
        "duoarea": "RGC",
        "area-name": "NA",
        "product": "EPJK",
        "product-name": "Kerosene-Type Jet Fuel",
        "process": "PF4",
        "process-name": "Spot Price FOB",
        "series": "EER_EPJK_PF4_RGC_DPG",
        "series-description": "U.S. Gulf Coast Kerosene-Type Jet Fuel Spot Price FOB (Dollars per Gallon)",
        "value": 3.913,
        "units": "$/GAL"
      },
      {
        "period": "2026-05-05",
        "duoarea": "RGC",
        "area-name": "NA",
        "product": "EPJK",
        "product-name": "Kerosene-Type Jet Fuel",
        "process": "PF4",
        "process-name": "Spot Price FOB",
        "series": "EER_EPJK_PF4_RGC_DPG",
        "series-description": "U.S. Gulf Coast Kerosene-Type Jet Fuel Spot Price FOB (Dollars per Gallon)",
        "value": 4.182,
        "units": "$/GAL"
      },
      {
        "period": "2026-05-04",
        "duoarea": "RGC",
        "area-name": "NA",
        "product": "EPJK",
        "product-name": "Kerosene-Type Jet Fuel",
        "process": "PF4",
        "process-name": "Spot Price FOB",
        "series": "EER_EPJK_PF4_RGC_DPG",
        "series-description": "U.S. Gulf Coast Kerosene-Type Jet Fuel Spot Price FOB (Dollars per Gallon)",
        "value": 4.163,
        "units": "$/GAL"
      },
      {
        "period": "2026-05-01",
        "duoarea": "RGC",
        "area-name": "NA",
        "product": "EPJK",
        "product-name": "Kerosene-Type Jet Fuel",
        "process": "PF4",
        "process-name": "Spot Price FOB",
        "series": "EER_EPJK_PF4_RGC_DPG",
        "series-description": "U.S. Gulf Coast Kerosene-Type Jet Fuel Spot Price FOB (Dollars per Gallon)",
        "value": 4.094,
        "units": "$/GAL"
      },
      {
        "period": "2026-04-30",
        "duoarea": "RGC",
        "area-name": "NA",
        "product": "EPJK",
        "product-name": "Kerosene-Type Jet Fuel",
        "process": "PF4",
        "process-name": "Spot Price FOB",
        "series": "EER_EPJK_PF4_RGC_DPG",
        "series-description": "U.S. Gulf Coast Kerosene-Type Jet Fuel Spot Price FOB (Dollars per Gallon)",
        "value": 4.287,
        "units": "$/GAL"
      },
      {
        "period": "2026-04-29",
        "duoarea": "RGC",
        "area-name": "NA",
        "product": "EPJK",
        "product-name": "Kerosene-Type Jet Fuel",
        "process": "PF4",
        "process-name": "Spot Price FOB",
        "series": "EER_EPJK_PF4_RGC_DPG",
        "series-description": "U.S. Gulf Coast Kerosene-Type Jet Fuel Spot Price FOB (Dollars per Gallon)",
        "value": 4.344,
        "units": "$/GAL"
      },
      {
        "period": "2026-04-28",
        "duoarea": "RGC",
        "area-name": "NA",
        "product": "EPJK",
        "product-name": "Kerosene-Type Jet Fuel",
        "process": "PF4",
        "process-name": "Spot Price FOB",
        "series": "EER_EPJK_PF4_RGC_DPG",
        "series-description": "U.S. Gulf Coast Kerosene-Type Jet Fuel Spot Price FOB (Dollars per Gallon)",
        "value": 4.047,
        "units": "$/GAL"
      },
      {
        "period": "2026-04-27",
        "duoarea": "RGC",
        "area-name": "NA",
        "product": "EPJK",
        "product-name": "Kerosene-Type Jet Fuel",
        "process": "PF4",
        "process-name": "Spot Price FOB",
        "series": "EER_EPJK_PF4_RGC_DPG",
        "series-description": "U.S. Gulf Coast Kerosene-Type Jet Fuel Spot Price FOB (Dollars per Gallon)",
        "value": 4.027,
        "units": "$/GAL"
      },
      {
        "period": "2026-04-24",
        "duoarea": "RGC",
        "area-name": "NA",
        "product": "EPJK",
        "product-name": "Kerosene-Type Jet Fuel",
        "process": "PF4",
        "process-name": "Spot Price FOB",
        "series": "EER_EPJK_PF4_RGC_DPG",
        "series-description": "U.S. Gulf Coast Kerosene-Type Jet Fuel Spot Price FOB (Dollars per Gallon)",
        "value": 4.024,
        "units": "$/GAL"
      },
      {
        "period": "2026-04-23",
        "duoarea": "RGC",
        "area-name": "NA",
        "product": "EPJK",
        "product-name": "Kerosene-Type Jet Fuel",
        "process": "PF4",
        "process-name": "Spot Price FOB",
        "series": "EER_EPJK_PF4_RGC_DPG",
        "series-description": "U.S. Gulf Coast Kerosene-Type Jet Fuel Spot Price FOB (Dollars per Gallon)",
        "value": 4.075,
        "units": "$/GAL"
      },
      {
        "period": "2026-04-22",
        "duoarea": "RGC",
        "area-name": "NA",
        "product": "EPJK",
        "product-name": "Kerosene-Type Jet Fuel",
        "process": "PF4",
        "process-name": "Spot Price FOB",
        "series": "EER_EPJK_PF4_RGC_DPG",
        "series-description": "U.S. Gulf Coast Kerosene-Type Jet Fuel Spot Price FOB (Dollars per Gallon)",
        "value": 3.96,
        "units": "$/GAL"
      },
      {
        "period": "2026-04-21",
        "duoarea": "RGC",
        "area-name": "NA",
        "product": "EPJK",
        "product-name": "Kerosene-Type Jet Fuel",
        "process": "PF4",
        "process-name": "Spot Price FOB",
        "series": "EER_EPJK_PF4_RGC_DPG",
        "series-description": "U.S. Gulf Coast Kerosene-Type Jet Fuel Spot Price FOB (Dollars per Gallon)",
        "value": 3.862,
        "units": "$/GAL"
      },
      {
        "period": "2026-04-20",
        "duoarea": "RGC",
        "area-name": "NA",
        "product": "EPJK",
        "product-name": "Kerosene-Type Jet Fuel",
        "process": "PF4",
        "process-name": "Spot Price FOB",
        "series": "EER_EPJK_PF4_RGC_DPG",
        "series-description": "U.S. Gulf Coast Kerosene-Type Jet Fuel Spot Price FOB (Dollars per Gallon)",
        "value": 3.608,
        "units": "$/GAL"
      },
      {
        "period": "2026-04-17",
        "duoarea": "RGC",
        "area-name": "NA",
        "product": "EPJK",
        "product-name": "Kerosene-Type Jet Fuel",
        "process": "PF4",
        "process-name": "Spot Price FOB",
        "series": "EER_EPJK_PF4_RGC_DPG",
        "series-description": "U.S. Gulf Coast Kerosene-Type Jet Fuel Spot Price FOB (Dollars per Gallon)",
        "value": 3.493,
        "units": "$/GAL"
      },
      {
        "period": "2026-04-16",
        "duoarea": "RGC",
        "area-name": "NA",
        "product": "EPJK",
        "product-name": "Kerosene-Type Jet Fuel",
        "process": "PF4",
        "process-name": "Spot Price FOB",
        "series": "EER_EPJK_PF4_RGC_DPG",
        "series-description": "U.S. Gulf Coast Kerosene-Type Jet Fuel Spot Price FOB (Dollars per Gallon)",
        "value": 3.864,
        "units": "$/GAL"
      },
      {
        "period": "2026-04-15",
        "duoarea": "RGC",
        "area-name": "NA",
        "product": "EPJK",
        "product-name": "Kerosene-Type Jet Fuel",
        "process": "PF4",
        "process-name": "Spot Price FOB",
        "series": "EER_EPJK_PF4_RGC_DPG",
        "series-description": "U.S. Gulf Coast Kerosene-Type Jet Fuel Spot Price FOB (Dollars per Gallon)",
        "value": 3.78,
        "units": "$/GAL"
      },
      {
        "period": "2026-04-14",
        "duoarea": "RGC",
        "area-name": "NA",
        "product": "EPJK",
        "product-name": "Kerosene-Type Jet Fuel",
        "process": "PF4",
        "process-name": "Spot Price FOB",
        "series": "EER_EPJK_PF4_RGC_DPG",
        "series-description": "U.S. Gulf Coast Kerosene-Type Jet Fuel Spot Price FOB (Dollars per Gallon)",
        "value": 3.659,
        "units": "$/GAL"
      },
      {
        "period": "2026-04-13",
        "duoarea": "RGC",
        "area-name": "NA",
        "product": "EPJK",
        "product-name": "Kerosene-Type Jet Fuel",
        "process": "PF4",
        "process-name": "Spot Price FOB",
        "series": "EER_EPJK_PF4_RGC_DPG",
        "series-description": "U.S. Gulf Coast Kerosene-Type Jet Fuel Spot Price FOB (Dollars per Gallon)",
        "value": 3.748,
        "units": "$/GAL"
      },
      {
        "period": "2026-04-10",
        "duoarea": "RGC",
        "area-name": "NA",
        "product": "EPJK",
        "product-name": "Kerosene-Type Jet Fuel",
        "process": "PF4",
        "process-name": "Spot Price FOB",
        "series": "EER_EPJK_PF4_RGC_DPG",
        "series-description": "U.S. Gulf Coast Kerosene-Type Jet Fuel Spot Price FOB (Dollars per Gallon)",
        "value": 3.685,
        "units": "$/GAL"
      },
      {
        "period": "2026-04-09",
        "duoarea": "RGC",
        "area-name": "NA",
        "product": "EPJK",
        "product-name": "Kerosene-Type Jet Fuel",
        "process": "PF4",
        "process-name": "Spot Price FOB",
        "series": "EER_EPJK_PF4_RGC_DPG",
        "series-description": "U.S. Gulf Coast Kerosene-Type Jet Fuel Spot Price FOB (Dollars per Gallon)",
        "value": 3.878,
        "units": "$/GAL"
      },
      {
        "period": "2026-04-08",
        "duoarea": "RGC",
        "area-name": "NA",
        "product": "EPJK",
        "product-name": "Kerosene-Type Jet Fuel",
        "process": "PF4",
        "process-name": "Spot Price FOB",
        "series": "EER_EPJK_PF4_RGC_DPG",
        "series-description": "U.S. Gulf Coast Kerosene-Type Jet Fuel Spot Price FOB (Dollars per Gallon)",
        "value": 3.825,
        "units": "$/GAL"
      },
      {
        "period": "2026-04-07",
        "duoarea": "RGC",
        "area-name": "NA",
        "product": "EPJK",
        "product-name": "Kerosene-Type Jet Fuel",
        "process": "PF4",
        "process-name": "Spot Price FOB",
        "series": "EER_EPJK_PF4_RGC_DPG",
        "series-description": "U.S. Gulf Coast Kerosene-Type Jet Fuel Spot Price FOB (Dollars per Gallon)",
        "value": 4.1,
        "units": "$/GAL"
      }
    ],
    "description": "EIA petroleum gas survey data",
    "id": "petroleum"
  },
  "request": {
    "command": "/v2/seriesid/PET.EER_EPJK_PF4_RGC_DPG.D",
    "params": {
      "frequency": "daily",
      "data": [
        "value"
      ],
      "facets": {
        "series": [
          "EER_EPJK_PF4_RGC_DPG"
        ]
      },
      "start": null,
      "end": null,
      "sort": [
        {
          "column": "period",
          "direction": "desc"
        }
      ],
      "offset": 0,
      "length": 30,
      "api_key": "LgCXrnMlTfUxj6yhcZzqZCmXLmC2dQLQtIqhO2jm"
    },
    "route": "petroleum/pri/spt"
  },
  "apiVersion": "2.1.12",
  "ExcelAddInVersion": "2.1.0"
}